skaak/__init__.py
skaak/board.py
skaak/chess.py
Skaak-0.12.5.dist-info/LICENSE
Skaak-0.12.5.dist-info/METADATA
Skaak-0.12.5.dist-info/WHEEL
Skaak-0.12.5.dist-info/top_level.txt
Skaak-0.12.5.dist-info/RECORD
