Metadata-Version: 2.1
Name: Skaak
Version: 0.12.5
Summary: A Python Chess Library
Home-page: UNKNOWN
Author: George Munyoro
Author-email: UNKNOWN
License: MIT
Platform: UNKNOWN
